odoo/addons/hr_timesheet_task_domain/README.rst
odoo/addons/hr_timesheet_task_domain/__init__.py
odoo/addons/hr_timesheet_task_domain/__manifest__.py
odoo/addons/hr_timesheet_task_domain/i18n/de.po
odoo/addons/hr_timesheet_task_domain/i18n/es.po
odoo/addons/hr_timesheet_task_domain/i18n/fr.po
odoo/addons/hr_timesheet_task_domain/i18n/hr_timesheet_task_domain.pot
odoo/addons/hr_timesheet_task_domain/i18n/it.po
odoo/addons/hr_timesheet_task_domain/i18n/pt_BR.po
odoo/addons/hr_timesheet_task_domain/models/__init__.py
odoo/addons/hr_timesheet_task_domain/models/account_analytic_line.py
odoo/addons/hr_timesheet_task_domain/readme/CONTRIBUTORS.md
odoo/addons/hr_timesheet_task_domain/readme/DESCRIPTION.md
odoo/addons/hr_timesheet_task_domain/static/description/icon.png
odoo/addons/hr_timesheet_task_domain/static/description/index.html
odoo_addon_hr_timesheet_task_domain-18.0.1.0.0.2.dist-info/METADATA
odoo_addon_hr_timesheet_task_domain-18.0.1.0.0.2.dist-info/WHEEL
odoo_addon_hr_timesheet_task_domain-18.0.1.0.0.2.dist-info/top_level.txt
odoo_addon_hr_timesheet_task_domain-18.0.1.0.0.2.dist-info/RECORD
